{"nodes":[{"label":"강동지","x":147.85032653808594,"y":72.65956115722656,"id":"15","attributes":{},"color":"rgb(0,0,0)","size":10.0},{"label":"홍참의","x":56.88518142700195,"y":-408.44610595703125,"id":"24","attributes":{},"color":"rgb(0,0,0)","size":10.0},{"label":"옥련_부","x":-444.30084228515625,"y":437.35272216796875,"id":"6","attributes":{},"color":"rgb(0,0,0)","size":10.0},{"label":"최본평","x":393.173828125,"y":174.6434326171875,"id":"11","attributes":{},"color":"rgb(0,0,0)","size":10.0},{"label":"이씨_부인","x":369.19610595703125,"y":-234.42636108398438,"id":"28","attributes":{},"color":"rgb(0,0,0)","size":10.0},{"label":"양자","x":-47.8630485534668,"y":402.7940673828125,"id":"4","attributes":{},"color":"rgb(0,0,0)","size":10.0},{"label":"옥남","x":466.0494384765625,"y":401.5455322265625,"id":"14","attributes":{},"color":"rgb(0,0,0)","size":10.0},{"label":"김승지_아들","x":317.58160400390625,"y":-136.750244140625,"id":"21","attributes":{},"color":"rgb(0,0,0)","size":10.0},{"label":"거복","x":401.85711669921875,"y":-182.07888793945312,"id":"23","attributes":{},"color":"rgb(0,0,0)","size":10.0},{"label":"옥순","x":-53.7446403503418,"y":296.3553466796875,"id":"13","attributes":{},"color":"rgb(0,0,0)","size":10.0},{"label":"김승지","x":-55.76963424682617,"y":179.31976318359375,"id":"19","attributes":{},"color":"rgb(0,0,0)","size":10.0},{"label":"춘애_모","x":-107.93684387207031,"y":-351.21539306640625,"id":"2","attributes":{},"color":"rgb(0,0,0)","size":10.0},{"label":"김광일","x":-117.40126037597656,"y":235.3974609375,"id":"10","attributes":{},"color":"rgb(0,0,0)","size":10.0},{"label":"옥련_모","x":173.80271911621094,"y":226.912353515625,"id":"7","attributes":{},"color":"rgb(0,0,0)","size":10.0},{"label":"김씨_부인","x":10.955310821533203,"y":-156.95266723632812,"id":"12","attributes":{},"color":"rgb(0,0,0)","size":10.0},{"label":"구원서","x":-461.60791015625,"y":-241.01272583007812,"id":"9","attributes":{},"color":"rgb(0,0,0)","size":10.0},{"label":"김승지_부인","x":-168.11448669433594,"y":428.55218505859375,"id":"20","attributes":{},"color":"rgb(0,0,0)","size":10.0},{"label":"남순","x":47.2357063293457,"y":-166.79638671875,"id":"27","attributes":{},"color":"rgb(0,0,0)","size":10.0},{"label":"옥련","x":219.10923767089844,"y":-310.1341552734375,"id":"5","attributes":{},"color":"rgb(0,0,0)","size":10.0},{"label":"후취_부인","x":-108.37330627441406,"y":25.293663024902344,"id":"3","attributes":{},"color":"rgb(0,0,0)","size":10.0},{"label":"길순","x":305.94921875,"y":-6.129218578338623,"id":"17","attributes":{},"color":"rgb(0,0,0)","size":10.0},{"label":"최춘애","x":-442.04669189453125,"y":-106.50537872314453,"id":"1","attributes":{},"color":"rgb(0,0,0)","size":10.0},{"label":"경상_부인","x":236.13145446777344,"y":299.61810302734375,"id":"8","attributes":{},"color":"rgb(0,0,0)","size":10.0},{"label":"침모","x":-27.847972869873047,"y":-357.671142578125,"id":"22","attributes":{},"color":"rgb(0,0,0)","size":10.0},{"label":"백돌","x":-498.5797424316406,"y":-186.70904541015625,"id":"26","attributes":{},"color":"rgb(0,0,0)","size":10.0},{"label":"최항래","x":-343.5652160644531,"y":-309.19158935546875,"id":"0","attributes":{},"color":"rgb(0,0,0)","size":10.0},{"label":"간동지_처","x":-339.43817138671875,"y":547.71533203125,"id":"18","attributes":{},"color":"rgb(0,0,0)","size":10.0},{"label":"강동지_처","x":273.96112060546875,"y":-227.81964111328125,"id":"16","attributes":{},"color":"rgb(0,0,0)","size":10.0},{"label":"박씨_부인","x":-88.50163269042969,"y":-405.83648681640625,"id":"25","attributes":{},"color":"rgb(0,0,0)","size":10.0}],"edges":[{"label":"약혼자","source":"5","target":"9","id":"16","attributes":{"relation_label":"약혼자","time_label":"옥련_미국_방문","time":"8"},"color":"rgb(0,0,0)","size":1.0},{"label":"계모녀","source":"1","target":"3","id":"5","attributes":{"relation_label":"계모녀","time_label":"춘애_모_사망_후","time":"2"},"color":"rgb(0,0,0)","size":1.0},{"label":"모녀","source":"12","target":"27","id":"59","attributes":{"relation_label":"모녀","time_label":"이씨_부인_치아산에_내쫓긴_후","time":"22"},"color":"rgb(0,0,0)","size":1.0},{"label":"부녀","source":"24","target":"27","id":"58","attributes":{"relation_label":"부녀","time_label":"이씨_부인_치아산에_내쫓긴_후","time":"22"},"color":"rgb(0,0,0)","size":1.0},{"label":"부부","source":"0","target":"2","id":"1","attributes":{"relation_label":"부부","time_label":"춘애_모_사망_전","time":"1"},"color":"rgb(0,0,0)","size":1.0},{"label":"부부","source":"7","target":"6","id":"12","attributes":{"relation_label":"부부","time_label":"청일전쟁_후","time":"4"},"color":"rgb(0,0,0)","size":1.0},{"label":"부부","source":"15","target":"18","id":"32","attributes":{"relation_label":"부부","time_label":"길순_사망_후","time":"14"},"color":"rgb(0,0,0)","size":1.0},{"label":"부부","source":"19","target":"20","id":"36","attributes":{"relation_label":"부부","time_label":"김승지_아들_사망_후","time":"16"},"color":"rgb(0,0,0)","size":1.0},{"label":"양부자","source":"0","target":"4","id":"6","attributes":{"relation_label":"양부자","time_label":"춘애_모_사망_후","time":"2"},"color":"rgb(0,0,0)","size":1.0},{"label":"부부","source":"11","target":"12","id":"18","attributes":{"relation_label":"부부","time_label":"최본평_사망_전","time":"9"},"color":"rgb(0,0,0)","size":1.0},{"label":"모자","source":"26","target":"25","id":"43","attributes":{"relation_label":"모자","time_label":"박씨_부인_사망_전","time":"18"},"color":"rgb(0,0,0)","size":1.0},{"label":"계모자","source":"26","target":"12","id":"52","attributes":{"relation_label":"계모자","time_label":"백돌과_이씨_부인_결혼_후","time":"20"},"color":"rgb(0,0,0)","size":1.0},{"label":"오누이","source":"14","target":"13","id":"23","attributes":{"relation_label":"오누이","time_label":"최본평_사망_후","time":"10"},"color":"rgb(0,0,0)","size":1.0},{"label":"부녀","source":"0","target":"1","id":"4","attributes":{"relation_label":"부녀","time_label":"춘애_모_사망_후","time":"2"},"color":"rgb(0,0,0)","size":1.0},{"label":"부자","source":"24","target":"26","id":"42","attributes":{"relation_label":"부자","time_label":"박씨_부인_사망_전","time":"18"},"color":"rgb(0,0,0)","size":1.0},{"label":"부녀","source":"0","target":"1","id":"0","attributes":{"relation_label":"부녀","time_label":"춘애_모_사망_전","time":"1"},"color":"rgb(0,0,0)","size":1.0},{"label":"모녀","source":"16","target":"17","id":"31","attributes":{"relation_label":"모녀","time_label":"길순_사망_전","time":"13"},"color":"rgb(0,0,0)","size":1.0},{"label":"모자","source":"24","target":"12","id":"45","attributes":{"relation_label":"모자","time_label":"박씨_부인_사망_후","time":"19"},"color":"rgb(0,0,0)","size":1.0},{"label":"부녀","source":"11","target":"13","id":"19","attributes":{"relation_label":"부녀","time_label":"최본평_사망_전","time":"9"},"color":"rgb(0,0,0)","size":1.0},{"label":"부부","source":"24","target":"12","id":"57","attributes":{"relation_label":"부부","time_label":"이씨_부인_치아산에_내쫓긴_후","time":"22"},"color":"rgb(0,0,0)","size":1.0},{"label":"부자","source":"19","target":"21","id":"35","attributes":{"relation_label":"부자","time_label":"김승지_아들_사망_전","time":"15"},"color":"rgb(0,0,0)","size":1.0},{"label":"부녀","source":"5","target":"6","id":"9","attributes":{"relation_label":"부녀","time_label":"청일전쟁_전","time":"3"},"color":"rgb(0,0,0)","size":1.0},{"label":"부녀","source":"15","target":"17","id":"30","attributes":{"relation_label":"부녀","time_label":"길순_사망_전","time":"13"},"color":"rgb(0,0,0)","size":1.0},{"label":"계모자","source":"26","target":"12","id":"48","attributes":{"relation_label":"계모자","time_label":"박씨_부인_사망_후","time":"19"},"color":"rgb(0,0,0)","size":1.0},{"label":"모녀","source":"12","target":"13","id":"20","attributes":{"relation_label":"모녀","time_label":"최본평_사망_전","time":"9"},"color":"rgb(0,0,0)","size":1.0},{"label":"부자","source":"24","target":"26","id":"44","attributes":{"relation_label":"부자","time_label":"박씨_부인_사망_후","time":"19"},"color":"rgb(0,0,0)","size":1.0},{"label":"모녀","source":"1","target":"2","id":"2","attributes":{"relation_label":"모녀","time_label":"춘애_모_사망_전","time":"1"},"color":"rgb(0,0,0)","size":1.0},{"label":"모자","source":"12","target":"14","id":"27","attributes":{"relation_label":"모자","time_label":"옥순_옥남_귀국_후","time":"12"},"color":"rgb(0,0,0)","size":1.0},{"label":"부부","source":"19","target":"20","id":"33","attributes":{"relation_label":"부부","time_label":"김승지_아들_사망_전","time":"15"},"color":"rgb(0,0,0)","size":1.0},{"label":"부자","source":"26","target":"24","id":"51","attributes":{"relation_label":"부자","time_label":"백돌과_이씨_부인_결혼_후","time":"20"},"color":"rgb(0,0,0)","size":1.0},{"label":"오누이","source":"13","target":"14","id":"28","attributes":{"relation_label":"오누이","time_label":"옥순_옥남_귀국_후","time":"12"},"color":"rgb(0,0,0)","size":1.0},{"label":"모녀","source":"12","target":"27","id":"47","attributes":{"relation_label":"모녀","time_label":"박씨_부인_사망_후","time":"19"},"color":"rgb(0,0,0)","size":1.0},{"label":"부부","source":"24","target":"25","id":"41","attributes":{"relation_label":"부부","time_label":"박씨_부인_사망_전","time":"18"},"color":"rgb(0,0,0)","size":1.0},{"label":"모자","source":"17","target":"23","id":"39","attributes":{"relation_label":"모자","time_label":"길순과_거복_사망_전","time":"17"},"color":"rgb(0,0,0)","size":1.0},{"label":"남매","source":"26","target":"27","id":"49","attributes":{"relation_label":"남매","time_label":"박씨_부인_사망_후","time":"19"},"color":"rgb(0,0,0)","size":1.0},{"label":"부부","source":"6","target":"7","id":"10","attributes":{"relation_label":"부부","time_label":"청일전쟁_전","time":"3"},"color":"rgb(0,0,0)","size":1.0},{"label":"양모녀","source":"5","target":"8","id":"14","attributes":{"relation_label":"양모녀","time_label":"옥련_일본_방문","time":"6"},"color":"rgb(0,0,0)","size":1.0},{"label":"모녀","source":"5","target":"7","id":"11","attributes":{"relation_label":"모녀","time_label":"청일전쟁_전","time":"3"},"color":"rgb(0,0,0)","size":1.0},{"label":"부자","source":"19","target":"23","id":"40","attributes":{"relation_label":"부자","time_label":"길순과_거복_사망_전","time":"17"},"color":"rgb(0,0,0)","size":1.0},{"label":"양모자","source":"3","target":"4","id":"7","attributes":{"relation_label":"양모자","time_label":"춘애_모_사망_후","time":"2"},"color":"rgb(0,0,0)","size":1.0},{"label":"모녀","source":"12","target":"13","id":"26","attributes":{"relation_label":"모녀","time_label":"옥순_옥남_귀국_후","time":"12"},"color":"rgb(0,0,0)","size":1.0},{"label":"부부","source":"28","target":"26","id":"60","attributes":{"relation_label":"부부","time_label":"백돌_귀국_후","time":"23"},"color":"rgb(0,0,0)","size":1.0},{"label":"모자","source":"20","target":"21","id":"34","attributes":{"relation_label":"모자","time_label":"김승지_아들_사망_전","time":"15"},"color":"rgb(0,0,0)","size":1.0},{"label":"오누이","source":"13","target":"14","id":"24","attributes":{"relation_label":"오누이","time_label":"옥순_옥남_미국_방문","time":"11"},"color":"rgb(0,0,0)","size":1.0},{"label":"모자","source":"12","target":"14","id":"22","attributes":{"relation_label":"모자","time_label":"최본평_사망_후","time":"10"},"color":"rgb(0,0,0)","size":1.0},{"source":"1","target":"4","id":"8","attributes":{"time_label":"춘애_모_사망_후","time":"2"},"color":"rgb(0,0,0)","size":1.0},{"label":"시누이","source":"28","target":"27","id":"56","attributes":{"relation_label":"시누이","time_label":"백돌_일본_유학","time":"21"},"color":"rgb(0,0,0)","size":1.0},{"label":"부녀","source":"5","target":"10","id":"17","attributes":{"relation_label":"부녀","time_label":"옥련_미국_방문","time":"8"},"color":"rgb(0,0,0)","size":1.0},{"source":"19","target":"22","id":"37","attributes":{"time_label":"김승지_부인_사망_후","time":"16"},"color":"rgb(0,0,0)","size":1.0},{"label":"시부모","source":"28","target":"24","id":"54","attributes":{"relation_label":"시부모","time_label":"백돌_일본_유학","time":"21"},"color":"rgb(0,0,0)","size":1.0},{"label":"모녀","source":"12","target":"13","id":"21","attributes":{"relation_label":"모녀","time_label":"최본평_사망_후","time":"10"},"color":"rgb(0,0,0)","size":1.0},{"label":"부부","source":"0","target":"3","id":"3","attributes":{"relation_label":"부부","time_label":"춘애_모_사망_후","time":"2"},"color":"rgb(0,0,0)","size":1.0},{"label":"남매","source":"26","target":"27","id":"53","attributes":{"relation_label":"남매","time_label":"백돌과_이씨_부인_결혼_후","time":"20"},"color":"rgb(0,0,0)","size":1.0},{"label":"부부","source":"15","target":"16","id":"29","attributes":{"relation_label":"부부","time_label":"길순_사망_전","time":"13"},"color":"rgb(0,0,0)","size":1.0},{"label":"시계모","source":"28","target":"12","id":"55","attributes":{"relation_label":"시계모","time_label":"백돌_일본_유학","time":"21"},"color":"rgb(0,0,0)","size":1.0},{"label":"부부","source":"26","target":"28","id":"50","attributes":{"relation_label":"부부","time_label":"백돌과_이씨_부인_결혼_후","time":"20"},"color":"rgb(0,0,0)","size":1.0},{"label":"부부(첩)","source":"19","target":"17","id":"38","attributes":{"relation_label":"부부(첩)","time_label":"길순과_거복_사망_전","time":"17"},"color":"rgb(0,0,0)","size":1.0},{"label":"부녀","source":"24","target":"27","id":"46","attributes":{"relation_label":"부녀","time_label":"박씨_부인_사망_후","time":"19"},"color":"rgb(0,0,0)","size":1.0}]}